miniscope_io-0.5.0.dist-info/METADATA
miniscope_io-0.5.0.dist-info/WHEEL
miniscope_io-0.5.0.dist-info/entry_points.txt
miniscope_io-0.5.0.dist-info/licenses/LICENSE
miniscope_io/__init__.py
miniscope_io/bit_operation.py
miniscope_io/cli/__init__.py
miniscope_io/cli/__main__.py
miniscope_io/cli/main.py
miniscope_io/cli/stream.py
miniscope_io/cli/update.py
miniscope_io/data/config/WLMS_v02_200px.yml
miniscope_io/device_update.py
miniscope_io/devices/XEM7310-A75/USBInterface-10mhz-J2_2-3v3-IEEE.bit
miniscope_io/devices/XEM7310-A75/USBInterface-12_5mhz-J2_2-3v3-IEEE.bit
miniscope_io/devices/XEM7310-A75/USBInterface-14_3mhz-J2_2-3v3-IEEE.bit
miniscope_io/devices/XEM7310-A75/USBInterface-3_03mhz-J2_2-3v3-IEEE.bit
miniscope_io/devices/XEM7310-A75/USBInterface-5mhz-J2_2-3v3-IEEE.bit
miniscope_io/devices/XEM7310-A75/USBInterface-6_67mhz-J2_2-3v3-IEEE.bit
miniscope_io/devices/XEM7310-A75/USBInterface-8_33mhz-J2_2-3v3-IEEE.bit
miniscope_io/devices/__init__.py
miniscope_io/devices/mocks.py
miniscope_io/devices/opalkelly.py
miniscope_io/exceptions.py
miniscope_io/formats/__init__.py
miniscope_io/formats/sdcard.py
miniscope_io/formats/stream.py
miniscope_io/io.py
miniscope_io/logging.py
miniscope_io/models/__init__.py
miniscope_io/models/buffer.py
miniscope_io/models/config.py
miniscope_io/models/data.py
miniscope_io/models/devupdate.py
miniscope_io/models/mixins.py
miniscope_io/models/models.py
miniscope_io/models/sdcard.py
miniscope_io/models/sinks.py
miniscope_io/models/stream.py
miniscope_io/plots/__init__.py
miniscope_io/plots/headers.py
miniscope_io/stream_daq.py
miniscope_io/types.py
miniscope_io/utils.py
miniscope_io/vendor/README.md
miniscope_io/vendor/__init__.py
miniscope_io/vendor/opalkelly/LICENSE
miniscope_io/vendor/opalkelly/README.md
miniscope_io/vendor/opalkelly/__init__.py
miniscope_io/vendor/opalkelly/linux/__init__.py
miniscope_io/vendor/opalkelly/linux/_ok.so
miniscope_io/vendor/opalkelly/linux/libokFrontPanel.so
miniscope_io/vendor/opalkelly/linux/ok.py
miniscope_io/vendor/opalkelly/linux/okFrontPanel.h
miniscope_io/vendor/opalkelly/linux/okFrontPanelDLL.h
miniscope_io/vendor/opalkelly/mac/__init__.py
miniscope_io-0.5.0.dist-info/RECORD
